CyberBookInterpreter
